lifetimer/__init__.py
lifetimer/__main__.py
lifetimer/cli.py
lifetimer/config/config.py
lifetimer/config/file.py
lifetimer/config/ini_file.py
lifetimer/lifetimer.py
lifetimer-0.1.0.dist-info/WHEEL
lifetimer-0.1.0.dist-info/entry_points.txt
lifetimer-0.1.0.dist-info/METADATA
lifetimer-0.1.0.dist-info/RECORD
