Metadata-Version: 2.1
Name: lifetimer
Version: 0.1.0
Summary: Lifespan timer
Home-page: https://github.com/kimfame/lifetimer.git
License: MIT
Author: kimfame
Author-email: renownkim@gmail.com
Requires-Python: >=3.11,<4.0
Classifier: Environment :: Console
Classifier: License :: OSI Approved :: MIT License
Classifier: Programming Language :: Python :: 3
Classifier: Programming Language :: Python :: 3.11
Classifier: Programming Language :: Python :: 3
Classifier: Programming Language :: Python :: 3 :: Only
Classifier: Programming Language :: Python :: 3.10
Classifier: Programming Language :: Python :: 3.11
Classifier: Programming Language :: Python :: 3.8
Classifier: Programming Language :: Python :: 3.9
Requires-Dist: click (>=8.1.3,<9.0.0)
Requires-Dist: platformdirs (>=3.0.0,<4.0.0)
Requires-Dist: yaspin (>=2.3.0,<3.0.0)
Project-URL: Repository, https://github.com/kimfame/lifetimer.git
